fine_python_lint/__init__.py
fine_python_lint/preset.toml
fine_python_lint-0.4.0.dist-info/METADATA
fine_python_lint-0.4.0.dist-info/WHEEL
fine_python_lint-0.4.0.dist-info/top_level.txt
fine_python_lint-0.4.0.dist-info/RECORD
